[
    {
      "id": 1,
      "name": "Anubhav Pathak",
      "image": "https://randomuser.me/api/portraits/men/1.jpg",
      "last_invoice": "16/08/24"
    },
    {
      "id": 2,
      "name": "Sahil Rawat",
      "image": "https://randomuser.me/api/portraits/men/2.jpg",
      "last_invoice": "16/08/24"
    },
    {
      "id": 3,
      "name": "Dhruv Sharma",
      "image": "https://randomuser.me/api/portraits/women/3.jpg",
      "last_invoice": "17/05/12"
    },
    {
      "id": 4,
      "name": "Divyanshu Singh",
      "image": "https://randomuser.me/api/portraits/men/4.jpg",
      "last_invoice": "18/10/30"
    },
    {
      "id": 5,
      "name": "Ankit khan",
      "image": "https://randomuser.me/api/portraits/women/5.jpg",
      "last_invoice": "19/04/01"
    },
    {
      "id": 6,
      "name": "Sakshi Rastogi",
      "image": "https://randomuser.me/api/portraits/men/6.jpg",
      "last_invoice": "20/11/27"
    },
    {
      "id": 7,
      "name": "Juilet devrani",
      "image": "https://randomuser.me/api/portraits/women/7.jpg",
      "last_invoice": "21/08/19"
    },
    {
      "id": 8,
      "name": "David Wu",
      "image": "https://randomuser.me/api/portraits/men/8.jpg",
      "last_invoice": "22/03/07"
    },
    {
      "id": 9,
      "name": "John Doe",
      "image": "https://randomuser.me/api/portraits/men/9.jpg",
      "last_invoice": "23/01/14"
    }
  ]
  